LICENSE
README.md
setup.py
src/tnmake/__init__.py
src/tnmake/logging.py
src/tnmake/main.py
src/tnmake/tnmake.py
src/tnmake.egg-info/PKG-INFO
src/tnmake.egg-info/SOURCES.txt
src/tnmake.egg-info/dependency_links.txt
src/tnmake.egg-info/entry_points.txt
src/tnmake.egg-info/requires.txt
src/tnmake.egg-info/top_level.txt