Metadata-Version: 2.1
Name: tnmake
Version: 0.2.0
Summary: Thumbnail!MAKER creates customisable thumbnails
Home-page: https://github.com/nschepsen/thumbnail-maker
Author: nschepsen
Author-email: nikolaj@schepsen.eu
License: GPLv3+
Keywords: library,video,tools
Platform: UNKNOWN
Classifier: Development Status :: 4 - Beta
Classifier: Environment :: Console
Classifier: Intended Audience :: End Users/Desktop
Classifier: License :: OSI Approved :: GNU General Public License v3 (GPLv3)
Classifier: Operating System :: POSIX :: Linux
Classifier: Programming Language :: Python :: 3
Classifier: Topic :: Home Automation
Classifier: Topic :: Multimedia :: Video
Classifier: Topic :: Utilities
License-File: LICENSE
